optimyze/__init__.py
optimyze/optimizers.py
optimyze-0.0.3.dist-info/METADATA
optimyze-0.0.3.dist-info/WHEEL
optimyze-0.0.3.dist-info/top_level.txt
optimyze-0.0.3.dist-info/RECORD
